django_notifications/__init__.py
django_notifications/admin.py
django_notifications/apps.py
django_notifications/migrations/0001_initial.py
django_notifications/migrations/0002_notification_app_id_object.py
django_notifications/migrations/__init__.py
django_notifications/models.py
django_notifications/signals.py
django_notifications/templates/admin/base_site.html
django_notifications/tests.py
django_notifications/urls.py
django_notifications/views.py
azzlem_django_notifications-0.1.887.dist-info/LICENSE
azzlem_django_notifications-0.1.887.dist-info/METADATA
azzlem_django_notifications-0.1.887.dist-info/WHEEL
azzlem_django_notifications-0.1.887.dist-info/RECORD
